setup.py
distributions/Binomialdistribution.py
distributions/Gaussiandistribution.py
distributions/Generaldistribution.py
distributions/__init__.py
fk_distributions.egg-info/PKG-INFO
fk_distributions.egg-info/SOURCES.txt
fk_distributions.egg-info/dependency_links.txt
fk_distributions.egg-info/not-zip-safe
fk_distributions.egg-info/top_level.txt