Metadata-Version: 1.0
Name: fk-distributions
Version: 0.1
Summary: Gaussian distributions as well as Binomial Distributions
Home-page: UNKNOWN
Author: UNKNOWN
Author-email: UNKNOWN
License: UNKNOWN
Platform: UNKNOWN
